{
	"configurations" : 
	[
		{
			"directories" : 
			[
				{
					"build" : ".",
					"minimumCMakeVersion" : 
					{
						"string" : "3.4.1"
					},
					"projectIndex" : 0,
					"source" : ".",
					"targetIndexes" : 
					[
						0
					]
				}
			],
			"name" : "Debug",
			"projects" : 
			[
				{
					"directoryIndexes" : 
					[
						0
					],
					"name" : "Project",
					"targetIndexes" : 
					[
						0
					]
				}
			],
			"targets" : 
			[
				{
					"directoryIndex" : 0,
					"id" : "cacau.wolf::@6890427a1f51a3e7e1df",
					"jsonFile" : "target-cacau.wolf-Debug-5e16559c4ba355694ab8.json",
					"name" : "cacau.wolf",
					"projectIndex" : 0
				}
			]
		}
	],
	"kind" : "codemodel",
	"paths" : 
	{
		"build" : "/Users/luizvaldetaro/TheWolf/Wolf3D/app/.cxx/Debug/i1rc221r/armeabi-v7a",
		"source" : "/Users/luizvaldetaro/TheWolf/Wolf3D/app"
	},
	"version" : 
	{
		"major" : 2,
		"minor" : 1
	}
}
